{
  "_format": "hh-sol-cache-2",
  "files": {
    "C:\\Users\\brons\\Documents\\blockchain-project\\contracts\\Lock.sol": {
      "lastModificationDate": 1750563984610,
      "contentHash": "afd0266806859cb74cbb27b6af41c5bd",
      "sourceName": "contracts/Lock.sol",
      "solcConfig": {
        "version": "0.8.30",
        "settings": {
          "optimizer": {
            "enabled": true,
            "runs": 200
          },
          "evmVersion": "paris",
          "outputSelection": {
            "*": {
              "*": [
                "abi",
                "evm.bytecode",
                "evm.deployedBytecode",
                "evm.methodIdentifiers",
                "metadata"
              ],
              "": [
                "ast"
              ]
            }
          }
        }
      },
      "imports": [],
      "versionPragmas": [
        "^0.8.30"
      ],
      "artifacts": [
        "Lock"
      ]
    },
    "C:\\Users\\brons\\Documents\\blockchain-project\\contracts\\MaliciousReceiver.sol": {
      "lastModificationDate": 1750805264604,
      "contentHash": "00f1e6c17e4f9b3f5374c6fd6e8c2771",
      "sourceName": "contracts/MaliciousReceiver.sol",
      "solcConfig": {
        "version": "0.8.30",
        "settings": {
          "optimizer": {
            "enabled": true,
            "runs": 200
          },
          "evmVersion": "paris",
          "outputSelection": {
            "*": {
              "*": [
                "abi",
                "evm.bytecode",
                "evm.deployedBytecode",
                "evm.methodIdentifiers",
                "metadata"
              ],
              "": [
                "ast"
              ]
            }
          }
        }
      },
      "imports": [],
      "versionPragmas": [
        "^0.8.0"
      ],
      "artifacts": [
        "IMyToken",
        "MaliciousReceiver"
      ]
    },
    "C:\\Users\\brons\\Documents\\blockchain-project\\contracts\\MyToken.sol": {
      "lastModificationDate": 1750803910861,
      "contentHash": "1bb12251ffba9c1e2c5380b51e06ad12",
      "sourceName": "contracts/MyToken.sol",
      "solcConfig": {
        "version": "0.8.30",
        "settings": {
          "optimizer": {
            "enabled": true,
            "runs": 200
          },
          "evmVersion": "paris",
          "outputSelection": {
            "*": {
              "*": [
                "abi",
                "evm.bytecode",
                "evm.deployedBytecode",
                "evm.methodIdentifiers",
                "metadata"
              ],
              "": [
                "ast"
              ]
            }
          }
        }
      },
      "imports": [
        "@openzeppelin/contracts/token/ERC20/ERC20.sol",
        "@openzeppelin/contracts/access/Ownable.sol",
        "@openzeppelin/contracts/utils/ReentrancyGuard.sol"
      ],
      "versionPragmas": [
        "^0.8.30"
      ],
      "artifacts": [
        "MyToken"
      ]
    },
    "C:\\Users\\brons\\Documents\\blockchain-project\\node_modules\\@openzeppelin\\contracts\\utils\\ReentrancyGuard.sol": {
      "lastModificationDate": 1750419226144,
      "contentHash": "190613e556d509d9e9a0ea43dc5d891d",
      "sourceName": "@openzeppelin/contracts/utils/ReentrancyGuard.sol",
      "solcConfig": {
        "version": "0.8.30",
        "settings": {
          "optimizer": {
            "enabled": true,
            "runs": 200
          },
          "evmVersion": "paris",
          "outputSelection": {
            "*": {
              "*": [
                "abi",
                "evm.bytecode",
                "evm.deployedBytecode",
                "evm.methodIdentifiers",
                "metadata"
              ],
              "": [
                "ast"
              ]
            }
          }
        }
      },
      "imports": [],
      "versionPragmas": [
        "^0.8.20"
      ],
      "artifacts": [
        "ReentrancyGuard"
      ]
    },
    "C:\\Users\\brons\\Documents\\blockchain-project\\node_modules\\@openzeppelin\\contracts\\access\\Ownable.sol": {
      "lastModificationDate": 1750419226137,
      "contentHash": "d3c790edc9ccf808a17c5a6cd13614fd",
      "sourceName": "@openzeppelin/contracts/access/Ownable.sol",
      "solcConfig": {
        "version": "0.8.30",
        "settings": {
          "optimizer": {
            "enabled": true,
            "runs": 200
          },
          "evmVersion": "paris",
          "outputSelection": {
            "*": {
              "*": [
                "abi",
                "evm.bytecode",
                "evm.deployedBytecode",
                "evm.methodIdentifiers",
                "metadata"
              ],
              "": [
                "ast"
              ]
            }
          }
        }
      },
      "imports": [
        "../utils/Context.sol"
      ],
      "versionPragmas": [
        "^0.8.20"
      ],
      "artifacts": [
        "Ownable"
      ]
    },
    "C:\\Users\\brons\\Documents\\blockchain-project\\node_modules\\@openzeppelin\\contracts\\token\\ERC20\\ERC20.sol": {
      "lastModificationDate": 1750419226044,
      "contentHash": "57d79df281f57bbb1b09214c7914f877",
      "sourceName": "@openzeppelin/contracts/token/ERC20/ERC20.sol",
      "solcConfig": {
        "version": "0.8.30",
        "settings": {
          "optimizer": {
            "enabled": true,
            "runs": 200
          },
          "evmVersion": "paris",
          "outputSelection": {
            "*": {
              "*": [
                "abi",
                "evm.bytecode",
                "evm.deployedBytecode",
                "evm.methodIdentifiers",
                "metadata"
              ],
              "": [
                "ast"
              ]
            }
          }
        }
      },
      "imports": [
        "./IERC20.sol",
        "./extensions/IERC20Metadata.sol",
        "../../utils/Context.sol",
        "../../interfaces/draft-IERC6093.sol"
      ],
      "versionPragmas": [
        "^0.8.20"
      ],
      "artifacts": [
        "ERC20"
      ]
    },
    "C:\\Users\\brons\\Documents\\blockchain-project\\node_modules\\@openzeppelin\\contracts\\utils\\Context.sol": {
      "lastModificationDate": 1750419225981,
      "contentHash": "67bfbc07588eb8683b3fd8f6f909563e",
      "sourceName": "@openzeppelin/contracts/utils/Context.sol",
      "solcConfig": {
        "version": "0.8.30",
        "settings": {
          "optimizer": {
            "enabled": true,
            "runs": 200
          },
          "evmVersion": "paris",
          "outputSelection": {
            "*": {
              "*": [
                "abi",
                "evm.bytecode",
                "evm.deployedBytecode",
                "evm.methodIdentifiers",
                "metadata"
              ],
              "": [
                "ast"
              ]
            }
          }
        }
      },
      "imports": [],
      "versionPragmas": [
        "^0.8.20"
      ],
      "artifacts": [
        "Context"
      ]
    },
    "C:\\Users\\brons\\Documents\\blockchain-project\\node_modules\\@openzeppelin\\contracts\\interfaces\\draft-IERC6093.sol": {
      "lastModificationDate": 1750419225995,
      "contentHash": "267d92fe4de67b1bdb3302c08f387dbf",
      "sourceName": "@openzeppelin/contracts/interfaces/draft-IERC6093.sol",
      "solcConfig": {
        "version": "0.8.30",
        "settings": {
          "optimizer": {
            "enabled": true,
            "runs": 200
          },
          "evmVersion": "paris",
          "outputSelection": {
            "*": {
              "*": [
                "abi",
                "evm.bytecode",
                "evm.deployedBytecode",
                "evm.methodIdentifiers",
                "metadata"
              ],
              "": [
                "ast"
              ]
            }
          }
        }
      },
      "imports": [],
      "versionPragmas": [
        "^0.8.20"
      ],
      "artifacts": [
        "IERC1155Errors",
        "IERC20Errors",
        "IERC721Errors"
      ]
    },
    "C:\\Users\\brons\\Documents\\blockchain-project\\node_modules\\@openzeppelin\\contracts\\token\\ERC20\\IERC20.sol": {
      "lastModificationDate": 1750419226111,
      "contentHash": "8f19f64d2adadf448840908bbaf431c8",
      "sourceName": "@openzeppelin/contracts/token/ERC20/IERC20.sol",
      "solcConfig": {
        "version": "0.8.30",
        "settings": {
          "optimizer": {
            "enabled": true,
            "runs": 200
          },
          "evmVersion": "paris",
          "outputSelection": {
            "*": {
              "*": [
                "abi",
                "evm.bytecode",
                "evm.deployedBytecode",
                "evm.methodIdentifiers",
                "metadata"
              ],
              "": [
                "ast"
              ]
            }
          }
        }
      },
      "imports": [],
      "versionPragmas": [
        "^0.8.20"
      ],
      "artifacts": [
        "IERC20"
      ]
    },
    "C:\\Users\\brons\\Documents\\blockchain-project\\node_modules\\@openzeppelin\\contracts\\token\\ERC20\\extensions\\IERC20Metadata.sol": {
      "lastModificationDate": 1750419226111,
      "contentHash": "794db3115001aa372c79326fcfd44b1f",
      "sourceName": "@openzeppelin/contracts/token/ERC20/extensions/IERC20Metadata.sol",
      "solcConfig": {
        "version": "0.8.30",
        "settings": {
          "optimizer": {
            "enabled": true,
            "runs": 200
          },
          "evmVersion": "paris",
          "outputSelection": {
            "*": {
              "*": [
                "abi",
                "evm.bytecode",
                "evm.deployedBytecode",
                "evm.methodIdentifiers",
                "metadata"
              ],
              "": [
                "ast"
              ]
            }
          }
        }
      },
      "imports": [
        "../IERC20.sol"
      ],
      "versionPragmas": [
        "^0.8.20"
      ],
      "artifacts": [
        "IERC20Metadata"
      ]
    },
    "C:\\Users\\brons\\Documents\\blockchain-project\\contracts\\UBaEducationCredentialsStore.sol": {
      "lastModificationDate": 1750851903991,
      "contentHash": "7cf607e9cf10e673e1a4a24c114d3108",
      "sourceName": "contracts/UBaEducationCredentialsStore.sol",
      "solcConfig": {
        "version": "0.8.30",
        "settings": {
          "optimizer": {
            "enabled": true,
            "runs": 200
          },
          "evmVersion": "paris",
          "outputSelection": {
            "*": {
              "*": [
                "abi",
                "evm.bytecode",
                "evm.deployedBytecode",
                "evm.methodIdentifiers",
                "metadata"
              ],
              "": [
                "ast"
              ]
            }
          }
        }
      },
      "imports": [
        "@openzeppelin/contracts/access/Ownable.sol",
        "@openzeppelin/contracts/token/ERC20/IERC20.sol"
      ],
      "versionPragmas": [
        "^0.8.0"
      ],
      "artifacts": [
        "UBaEducationCredentialsStore"
      ]
    }
  }
}
